transtractor-0.9.1.dist-info/METADATA
transtractor-0.9.1.dist-info/WHEEL
transtractor-0.9.1.dist-info/licenses/LICENSE
transtractor.libs/libgcc_s-39080030.so.1
transtractor/__init__.py
transtractor/configs/au/cba__credit_card__1.json
transtractor/configs/au/cba__debit__1.json
transtractor/configs/au/cba__loan__1.json
transtractor/configs/au/nab__classic_banking__1.json
transtractor/exceptions.py
transtractor/parser.py
transtractor/structs/__init__.py
transtractor/structs/statement_data.py
transtractor/structs/transaction.py
transtractor/transtractor.cpython-39-aarch64-linux-gnu.so
transtractor/transtractor.pyi
transtractor/utils/__init__.py
transtractor/utils/default_configs.py
transtractor/utils/extract.py
transtractor/utils/testing.py
transtractor-0.9.1.dist-info/RECORD
