Metadata-Version: 2.4
Name: transtractor
Version: 0.9.1
Classifier: Development Status :: 4 - Beta
Classifier: Intended Audience :: Developers
Classifier: Intended Audience :: Financial and Insurance Industry
Classifier: License :: OSI Approved :: MIT License
Classifier: Programming Language :: Python :: 3
Classifier: Programming Language :: Python :: 3.9
Classifier: Programming Language :: Python :: 3.10
Classifier: Programming Language :: Python :: 3.11
Classifier: Programming Language :: Python :: 3.12
Classifier: Programming Language :: Python :: 3.13
Classifier: Programming Language :: Python :: 3.14
Classifier: Programming Language :: Rust
Classifier: Programming Language :: Python :: Implementation :: CPython
Classifier: Programming Language :: Python :: Implementation :: PyPy
Classifier: Topic :: Office/Business :: Financial
Classifier: Topic :: Software Development :: Libraries :: Python Modules
Requires-Dist: pdfplumber>=0.11.8,<0.12.0
License-File: LICENSE
Summary: Universal PDF bank statement parsing library
Keywords: pdf,bank,statement,parser,transaction,extraction,csv
Author-email: Daniel Weber <develop@transtractor.net>
Requires-Python: >=3.9
Project-URL: Homepage, https://github.com/transtractor/transtractor-lib
Project-URL: Documentation, https://transtractor-lib.readthedocs.io
Project-URL: Repository, https://github.com/transtractor/transtractor-lib
Project-URL: Issues, https://github.com/transtractor/transtractor-lib/issues
